{
  "Italy": {
    "id": "3265bb91a1202f7d8416",
    "url": "https://upload.wikimedia.org/wikipedia/en/0/03/Flag_of_Italy.svg"
  },
  "Bulgaria": {
    "id": "559748a6a47efc633bf0",
    "url": "https://upload.wikimedia.org/wikipedia/commons/9/9a/Flag_of_Bulgaria.svg"
  },
  "Croatia": {
    "id": "99ce7a8c3983570f86ae",
    "url": "https://upload.wikimedia.org/wikipedia/commons/1/1b/Flag_of_Croatia.svg"
  },
  "Estonia": {
    "id": "a87e92a1a7538a226103",
    "url": "https://upload.wikimedia.org/wikipedia/commons/8/8f/Flag_of_Estonia.svg"
  },
  "Andorra": {
    "id": "239e3b951d01e26e433e",
    "url": "https://upload.wikimedia.org/wikipedia/commons/1/19/Flag_of_Andorra.svg"
  },
  "Armenia": {
    "id": "9dc75b2536fbf84a2dad",
    "url": "https://upload.wikimedia.org/wikipedia/commons/2/2f/Flag_of_Armenia.svg"
  },
  "Moldova": {
    "id": "dc642b8a1a1164751a94",
    "url": "https://upload.wikimedia.org/wikipedia/commons/2/27/Flag_of_Moldova.svg"
  },
  "Luxembourg": {
    "id": "eb3fed4d19316118acb8",
    "url": "https://upload.wikimedia.org/wikipedia/commons/d/da/Flag_of_Luxembourg.svg"
  },
  "Vatican City": {
    "id": "89687e792552708bb29b",
    "url": "https://upload.wikimedia.org/wikipedia/commons/f/fc/Flag_of_the_Vatican_City_%282001%E2%80%932023%29.svg"
  },
  "Poland": {
    "id": "732e22c713a7b7b99e3f",
    "url": "https://upload.wikimedia.org/wikipedia/en/1/12/Flag_of_Poland.svg"
  },
  "Latvia": {
    "id": "997cec9bf5dbbe59587d",
    "url": "https://upload.wikimedia.org/wikipedia/commons/8/84/Flag_of_Latvia.svg"
  },
  "Iceland": {
    "id": "20c72eb56ac1611146fc",
    "url": "https://upload.wikimedia.org/wikipedia/commons/c/ce/Flag_of_Iceland.svg"
  },
  "Lithuania": {
    "id": "b30908fff86df830d570",
    "url": "https://upload.wikimedia.org/wikipedia/commons/1/11/Flag_of_Lithuania.svg"
  },
  "Monaco": {
    "id": "722b4fe6e8ea5ab92601",
    "url": "https://upload.wikimedia.org/wikipedia/commons/e/ea/Flag_of_Monaco.svg"
  },
  "Finland": {
    "id": "fe581f985856b8cc936b",
    "url": "https://upload.wikimedia.org/wikipedia/commons/b/bc/Flag_of_Finland.svg"
  },
  "Belarus": {
    "id": "c71268a0528b0a5654e1",
    "url": "https://upload.wikimedia.org/wikipedia/commons/8/85/Flag_of_Belarus.svg"
  },
  "Netherlands": {
    "id": "4ea2367c0b473067b8b0",
    "url": "https://upload.wikimedia.org/wikipedia/commons/2/20/Flag_of_the_Netherlands.svg"
  },
  "Portugal": {
    "id": "6b01e7f894d1b243dc9a",
    "url": "https://upload.wikimedia.org/wikipedia/commons/5/5c/Flag_of_Portugal.svg"
  },
  "Sweden": {
    "id": "35c24626a201847d09c4",
    "url": "https://upload.wikimedia.org/wikipedia/en/4/4c/Flag_of_Sweden.svg"
  },
  "Czech Republic": {
    "id": "df0f4cd8ad279cf0ef72",
    "url": "https://upload.wikimedia.org/wikipedia/commons/c/cb/Flag_of_the_Czech_Republic.svg"
  },
  "United Kingdom": {
    "id": "fc08296f24e1168bb93f",
    "url": "https://upload.wikimedia.org/wikipedia/en/a/ae/Flag_of_the_United_Kingdom.svg"
  },
  "Austria": {
    "id": "aa9732d096c37abf7a77",
    "url": "https://upload.wikimedia.org/wikipedia/commons/4/41/Flag_of_Austria.svg"
  },
  "Slovenia": {
    "id": "43651566dedad28f6d6b",
    "url": "https://upload.wikimedia.org/wikipedia/commons/f/f0/Flag_of_Slovenia.svg"
  },
  "Kazakhstan": {
    "id": "a3cf887a68b51d3d7fe4",
    "url": "https://upload.wikimedia.org/wikipedia/commons/d/d3/Flag_of_Kazakhstan.svg"
  },
  "Albania": {
    "id": "a577b557788791be18c7",
    "url": "https://upload.wikimedia.org/wikipedia/commons/3/36/Flag_of_Albania.svg"
  },
  "Georgia": {
    "id": "de60be57e5cd2eeaf98a",
    "url": "https://upload.wikimedia.org/wikipedia/commons/0/0f/Flag_of_Georgia.svg"
  },
  "San Marino": {
    "id": "13de15b9cdb8755514aa",
    "url": "https://upload.wikimedia.org/wikipedia/commons/b/b1/Flag_of_San_Marino.svg"
  },
  "Serbia": {
    "id": "8d0eeef99da34f67316c",
    "url": "https://upload.wikimedia.org/wikipedia/commons/f/ff/Flag_of_Serbia.svg"
  },
  "Liechtenstein": {
    "id": "f03be2a83ebc3fba8a33",
    "url": "https://upload.wikimedia.org/wikipedia/commons/4/47/Flag_of_Liechtenstein.svg"
  },
  "Hungary": {
    "id": "12cd1ef0d363fe23d2a2",
    "url": "https://upload.wikimedia.org/wikipedia/commons/c/c1/Flag_of_Hungary.svg"
  },
  "Ukraine": {
    "id": "d52bf3aab76e6429beda",
    "url": "https://upload.wikimedia.org/wikipedia/commons/4/49/Flag_of_Ukraine.svg"
  },
  "Spain": {
    "id": "560939adb282c866e268",
    "url": "https://upload.wikimedia.org/wikipedia/commons/8/89/Bandera_de_Espa%C3%B1a.svg"
  },
  "Bosnia and Herzegovina": {
    "id": "abc495749163fbbaf038",
    "url": "https://upload.wikimedia.org/wikipedia/commons/b/bf/Flag_of_Bosnia_and_Herzegovina.svg"
  },
  "Turkey": {
    "id": "d1dc4739595710a1f3cd",
    "url": "https://upload.wikimedia.org/wikipedia/commons/b/b4/Flag_of_Turkey.svg"
  },
  "Russia": {
    "id": "423edd6612622b2da457",
    "url": "https://upload.wikimedia.org/wikipedia/en/f/f3/Flag_of_Russia.svg"
  },
  "Belgium": {
    "id": "c561b787d961bcf4ad11",
    "url": "https://upload.wikimedia.org/wikipedia/commons/6/65/Flag_of_Belgium.svg"
  },
  "North Macedonia": {
    "id": "47f0212d67e5f6850881",
    "url": "https://upload.wikimedia.org/wikipedia/commons/7/79/Flag_of_North_Macedonia.svg"
  },
  "Montenegro": {
    "id": "b1c6fbb1ac2c9fec1a8b",
    "url": "https://upload.wikimedia.org/wikipedia/commons/6/64/Flag_of_Montenegro.svg"
  },
  "Slovakia": {
    "id": "dfea90a4a9a43ad4f26c",
    "url": "https://upload.wikimedia.org/wikipedia/commons/e/e6/Flag_of_Slovakia.svg"
  },
  "Azerbaijan": {
    "id": "b7c07bfed54e4b534fcb",
    "url": "https://upload.wikimedia.org/wikipedia/commons/d/dd/Flag_of_Azerbaijan.svg"
  },
  "France": {
    "id": "ec25229531ee40b11faa",
    "url": "https://upload.wikimedia.org/wikipedia/commons/9/93/Flag_of_France_%281794%E2%80%931815%2C_1830%E2%80%931974%29.svg"
  },
  "Germany": {
    "id": "59d60d4bf97267e03b79",
    "url": "https://upload.wikimedia.org/wikipedia/en/b/ba/Flag_of_Germany.svg"
  },
  "Malta": {
    "id": "7b877f517726fc79b5b0",
    "url": "https://upload.wikimedia.org/wikipedia/commons/7/73/Flag_of_Malta.svg"
  },
  "Cyprus": {
    "id": "d4808cb01e3f7c2b6a0f",
    "url": "https://upload.wikimedia.org/wikipedia/commons/d/d4/Flag_of_Cyprus.svg"
  },
  "Greece": {
    "id": "1715b57ea7d8b1a7eca2",
    "url": "https://upload.wikimedia.org/wikipedia/commons/5/5c/Flag_of_Greece.svg"
  },
  "Romania": {
    "id": "4783a399348b4d4fbbe1",
    "url": "https://upload.wikimedia.org/wikipedia/commons/7/73/Flag_of_Romania.svg"
  },
  "Norway": {
    "id": "0dc09d6ab2c2c8e9cd65",
    "url": "https://upload.wikimedia.org/wikipedia/commons/d/d9/Flag_of_Norway.svg"
  },
  "Ireland": {
    "id": "7c9d41f758e8349ca753",
    "url": "https://upload.wikimedia.org/wikipedia/commons/4/45/Flag_of_Ireland.svg"
  },
  "Switzerland": {
    "id": "2cd503d4a5177e7f8b41",
    "url": "https://upload.wikimedia.org/wikipedia/commons/f/f3/Flag_of_Switzerland.svg"
  },
  "Denmark": {
    "id": "f7e3e47fcb94cbe16f86",
    "url": "https://upload.wikimedia.org/wikipedia/commons/9/9c/Flag_of_Denmark.svg"
  }
}